{
    "ohloh": {
        "main_language": null, 
        "max_month": "2014-02-01T00:00:00Z", 
        "description": "A list of public BitTorrent Sync keys", 
        "tags": [], 
        "total_code_lines": 0, 
        "total_contributor_count": 5, 
        "twelve_month_contributor_count": 5, 
        "updated_at": "2014-04-09T17:39:32Z", 
        "analysis": "19540897", 
        "min_month": "2013-04-01T00:00:00Z", 
        "factoids": [
            "Average size development team", 
            "Short source control history"
        ], 
        "twelve_month_commit_count": 18, 
        "total_commit_count": 18, 
        "id": "658281", 
        "name": "btsync-keys"
    }, 
    "description": "[BitTorrent Sync](http://www.bittorrent.com/sync) by BitTorrent Labs. Easy and effortless file replication between computers (and mobile devices) without using the cloud, so the only limit is available storage. All data transfers are encrypted. Works on Windows, Linux, OSX, Android and iOS. Recently they've [opened up their API](http://www.bittorrent.com/sync/developers/api) to developers.", 
    "name": "BitTorrent Sync"
}